morph_spines/__init__.py
morph_spines/core/__init__.py
morph_spines/core/h5_schema.py
morph_spines/core/morphology_with_spines.py
morph_spines/core/soma.py
morph_spines/core/spines.py
morph_spines/utils/__init__.py
morph_spines/utils/morph_spine_loader.py
morph_spines-0.5.0.dist-info/licenses/LICENSE
morph_spines-0.5.0.dist-info/METADATA
morph_spines-0.5.0.dist-info/WHEEL
morph_spines-0.5.0.dist-info/top_level.txt
morph_spines-0.5.0.dist-info/RECORD
